{
  "releaseDate": "2026-07-18",
  "tools": [
    {
      "index": 24,
      "slug": "hash-generator",
      "title": "텍스트·파일 해시 생성기",
      "englishTitle": "Text and file hash generator",
      "type": "converter",
      "description": "텍스트나 파일을 선택해 SHA-256·SHA-384·SHA-512 해시값을 브라우저에서 계산합니다.",
      "actionTitle": "해시값 계산하기",
      "features": ["텍스트와 파일 입력", "SHA-256·SHA-384·SHA-512", "대문자·소문자 출력", "결과 복사"],
      "inputs": [{"id":"source","label":"텍스트 또는 파일","type":"text-file"},{"id":"algorithm","label":"해시 알고리즘","type":"radio"}],
      "steps": ["텍스트를 입력하거나 파일을 선택합니다.", "해시 알고리즘과 출력 형식을 선택합니다.", "계산한 해시값을 복사합니다."],
      "details": ["해시는 같은 입력에서 항상 같은 길이의 식별값을 만드는 방식입니다. 다운로드 파일의 무결성을 대조하거나 두 텍스트가 같은지 확인할 때 원문 전체를 비교하지 않고도 사용할 수 있습니다.", "입력한 텍스트와 파일은 서버로 전송하지 않고 현재 브라우저의 Web Crypto 기능으로 처리합니다. 해시값은 암호화된 원문이 아니므로 다시 복원할 수 없으며 비밀번호 저장 용도로 단독 사용해서는 안 됩니다."],
      "faq": [{"question":"파일이 서버로 전송되나요?","answer":"아니요. 선택한 파일은 현재 브라우저에서만 읽어 해시를 계산합니다."},{"question":"어떤 알고리즘을 선택하면 되나요?","answer":"일반적인 무결성 확인에는 SHA-256이 널리 쓰이며, 상대방이 지정한 알고리즘이 있으면 같은 항목을 선택하세요."},{"question":"같은 파일인데 해시가 다를 수 있나요?","answer":"파일 내용이 한 바이트라도 달라지면 해시가 달라집니다. 파일명은 계산 결과에 영향을 주지 않습니다."},{"question":"해시로 원문을 복원할 수 있나요?","answer":"아니요. 이 도구의 해시는 원문으로 되돌리는 인코딩이 아닙니다."}],
      "tags": ["해시", "SHA256", "파일무결성", "체크섬", "브라우저도구"],
      "keywords": ["해시 생성기","SHA-256 생성","SHA-384 계산","SHA-512 계산","파일 해시","텍스트 해시","체크섬 계산","파일 무결성 확인","hash generator","SHA256 online","file checksum","text checksum","Web Crypto hash","로컬 해시 계산","파일 비교 해시","대문자 해시","소문자 해시","브라우저 해시","다운로드 검증","checksum tool","SHA 해시 복사","파일 내용 확인","해시값 만들기","서버 전송 없는 해시"],
      "summary": "텍스트와 파일의 SHA 계열 해시를 로컬에서 계산하는 최초 버전입니다.",
      "changes": ["텍스트·파일 SHA-256·384·512 계산", "대소문자 출력과 복사 대체 처리", "KOR / ENG와 파일 크기 제한"],
      "qa": ["빈 입력·텍스트·파일 상태 확인", "375px 모바일 가로 넘침 확인", "KOR / ENG와 iframe 높이 확인"]
    },
    {
      "index": 25,
      "slug": "number-base-converter",
      "title": "2진수·16진수 진법 변환기",
      "englishTitle": "Number base converter",
      "type": "converter",
      "description": "2진수·8진수·10진수·16진수를 정수 정밀도 손실 없이 서로 변환합니다.",
      "actionTitle": "진법 변환하기",
      "features": ["2·8·10·16진수 입력", "BigInt 정밀 변환", "네 진법 동시 결과", "접두어 표시 선택"],
      "inputs": [{"id":"value","label":"변환할 정수","type":"text"},{"id":"base","label":"입력 진법","type":"radio"}],
      "steps": ["입력값과 현재 진법을 선택합니다.", "필요하면 0x 같은 접두어 표시를 선택합니다.", "네 가지 진법 결과를 확인하고 복사합니다."],
      "details": ["진법 변환기는 같은 정수를 2진수, 8진수, 10진수, 16진수 표기로 나란히 보여 줍니다. 개발 중 비트값이나 색상·주소 값의 정수 표현을 대조할 때 유용합니다.", "브라우저의 BigInt를 사용해 일반 숫자형의 안전 정수 범위를 넘는 값도 정밀도 손실 없이 처리합니다. 소수는 지원하지 않으며 선택한 진법에 맞지 않는 문자가 있으면 입력 위치 가까이에서 안내합니다."],
      "faq": [{"question":"큰 정수도 정확히 변환되나요?","answer":"네. BigInt로 처리해 지원 길이 안에서는 자릿수를 반올림하지 않습니다."},{"question":"음수도 입력할 수 있나요?","answer":"네. 맨 앞의 빼기 기호를 유지해 각 진법으로 변환합니다."},{"question":"0x를 입력해도 되나요?","answer":"16진수를 선택했을 때 0x 접두어를 허용하며, 2진수의 0b와 8진수의 0o도 지원합니다."},{"question":"소수도 변환되나요?","answer":"아니요. 이 도구는 정수 진법 변환에 집중합니다."}],
      "tags": ["진법변환", "2진수", "16진수", "10진수", "개발도구"],
      "keywords": ["진법 변환기","2진수 변환","16진수 변환","10진수 변환","8진수 변환","binary converter","hex converter","decimal to hex","hex to decimal","binary to decimal","BigInt converter","정수 변환","0x 변환","0b 변환","개발자 계산기","비트 값 변환","진수 계산","base converter","number radix","큰 정수 변환","음수 진법","2진법 계산","16진법 계산","접두어 표시"],
      "summary": "네 가지 정수 진법을 정밀하게 상호 변환하는 최초 버전입니다.",
      "changes": ["2·8·10·16진수 상호 변환", "BigInt 기반 큰 정수·음수 처리", "접두어 선택과 전체 결과 복사"],
      "qa": ["잘못된 숫자·큰 정수·음수 확인", "375px 모바일 가로 넘침 확인", "KOR / ENG와 iframe 높이 확인"]
    },
    {
      "index": 26,
      "slug": "filename-sanitizer",
      "title": "안전한 파일명 정리기",
      "englishTitle": "Safe filename sanitizer",
      "type": "converter",
      "description": "파일명에서 사용할 수 없는 문자와 불필요한 공백을 정리해 복사 가능한 이름으로 바꿉니다.",
      "actionTitle": "파일명 정리하기",
      "features": ["Windows·macOS 호환 문자 정리", "확장자 보존", "공백·구분자 선택", "변경 내용 안내"],
      "inputs": [{"id":"filename","label":"원본 파일명","type":"text"},{"id":"separator","label":"공백 처리","type":"radio"}],
      "steps": ["정리할 파일명을 입력합니다.", "공백을 유지하거나 하이픈·밑줄로 바꿀지 선택합니다.", "미리보기와 변경 내역을 확인한 뒤 복사합니다."],
      "details": ["파일명 정리기는 운영체제에서 예약되거나 경로로 해석될 수 있는 문자를 제거하고 연속된 공백과 구분자를 보기 좋게 정리합니다. 문서 공유나 웹 업로드 전에 이름 오류를 줄일 수 있습니다.", "파일 내용이나 실제 파일을 변경하지 않고 입력한 이름 문자열만 다룹니다. 확장자는 가능한 한 유지하며 Windows 예약 이름처럼 저장에 실패할 수 있는 경우에는 안전한 접두어를 붙여 안내합니다."],
      "faq": [{"question":"실제 파일 이름이 바로 바뀌나요?","answer":"아니요. 안전한 이름을 만들어 보여 줄 뿐이며 복사 후 직접 이름을 바꾸면 됩니다."},{"question":"확장자는 유지되나요?","answer":"네. 마지막 점 뒤의 일반적인 확장자는 유지하고 파일명 부분을 중심으로 정리합니다."},{"question":"한글 파일명도 사용할 수 있나요?","answer":"네. 한글과 대부분의 유니코드 문자는 유지합니다."},{"question":"왜 CON 같은 이름이 바뀌나요?","answer":"일부 이름은 Windows 예약 장치명이라 저장할 수 없으므로 안전한 접두어를 붙입니다."}],
      "tags": ["파일명", "파일이름정리", "윈도우파일명", "문자정리", "업로드도구"],
      "keywords": ["파일명 정리기","파일 이름 변경","안전한 파일명","특수문자 제거","윈도우 파일명","macOS 파일명","filename sanitizer","safe filename","invalid filename characters","파일명 공백 제거","파일명 하이픈","파일명 밑줄","확장자 유지","CON 파일명","예약 파일명","업로드 파일 이름","경로 문자 제거","파일명 슬래시 제거","파일명 콜론 제거","이름 정리","한글 파일명","파일명 미리보기","문서 이름 정리","브라우저 파일명 도구"],
      "summary": "운영체제 호환 파일명을 미리 만들어 복사하는 최초 버전입니다.",
      "changes": ["금지 문자·예약 이름 안전 처리", "확장자 보존과 공백 구분자 선택", "변경 내역과 복사 대체 처리"],
      "qa": ["예약 이름·확장자·한글 입력 확인", "375px 모바일 가로 넘침 확인", "KOR / ENG와 iframe 높이 확인"]
    },
    {
      "index": 27,
      "slug": "lorem-ipsum-generator",
      "title": "Lorem Ipsum 문장 생성기",
      "englishTitle": "Lorem Ipsum generator",
      "type": "template-generator",
      "description": "레이아웃 테스트에 쓸 Lorem Ipsum 문단을 원하는 개수와 길이로 생성합니다.",
      "actionTitle": "자리표시 문장 만들기",
      "features": ["1~10개 문단", "짧게·보통·길게", "첫 문장 고정 선택", "전체 결과 복사"],
      "inputs": [{"id":"paragraphs","label":"문단 수","type":"range"},{"id":"length","label":"문단 길이","type":"radio"}],
      "steps": ["필요한 문단 수를 슬라이더로 정합니다.", "문단 길이와 첫 문장 옵션을 선택합니다.", "새 문장을 생성해 디자인 시안에 복사합니다."],
      "details": ["Lorem Ipsum은 실제 내용이 준비되기 전에 글자 밀도와 줄바꿈, 카드 높이를 확인할 때 쓰는 자리표시 문장입니다. 문단 수와 길이를 바꿔 모바일·데스크톱 레이아웃을 빠르게 시험할 수 있습니다.", "생성 결과는 브라우저 안에서 임의로 조합되며 개인정보나 외부 문서를 사용하지 않습니다. 최종 공개 문서에서는 자리표시 문장을 실제 사용자용 내용으로 교체해야 합니다."],
      "faq": [{"question":"매번 같은 문장이 나오나요?","answer":"문장 순서를 다시 섞어 생성하므로 일부 구성이 달라질 수 있습니다."},{"question":"첫 문장을 Lorem ipsum으로 시작할 수 있나요?","answer":"네. 첫 문장 고정 옵션을 선택하면 전통적인 시작 문구를 앞에 둡니다."},{"question":"한국어 자리표시 문장도 제공하나요?","answer":"현재는 시각 디자인에서 널리 쓰이는 라틴어 형태에 집중합니다."},{"question":"생성한 문장을 실제 본문에 써도 되나요?","answer":"시안과 레이아웃 테스트용이며 공개 전에는 실제 내용으로 바꾸는 것이 좋습니다."}],
      "tags": ["LoremIpsum", "더미텍스트", "자리표시문장", "디자인도구", "문장생성"],
      "keywords": ["Lorem Ipsum 생성기","로렘 입숨","더미 텍스트","자리표시 문장","placeholder text","lorem generator","dummy text","디자인 시안 텍스트","문단 생성기","레이아웃 테스트","웹 디자인 문장","출판 더미 글","1문단 lorem","여러 문단 생성","짧은 lorem ipsum","긴 lorem ipsum","텍스트 채우기","UI 테스트 문장","카드 높이 테스트","줄바꿈 테스트","랜덤 문장 생성","라틴어 더미","복사 가능한 lorem","브라우저 문장 생성"],
      "summary": "문단 수와 길이를 조절하는 Lorem Ipsum 최초 버전입니다.",
      "changes": ["1~10개 Lorem Ipsum 문단 생성", "세 가지 문단 길이와 첫 문장 옵션", "KOR / ENG와 전체 복사"],
      "qa": ["1·10개 문단과 길이별 결과 확인", "375px 모바일 가로 넘침 확인", "KOR / ENG와 iframe 높이 확인"]
    },
    {
      "index": 28,
      "slug": "css-clamp-calculator",
      "title": "CSS clamp 반응형 계산기",
      "englishTitle": "CSS clamp calculator",
      "type": "calculator",
      "description": "최소·최대 크기와 뷰포트 범위를 입력해 반응형 CSS clamp 식을 계산합니다.",
      "actionTitle": "clamp 식 계산하기",
      "features": ["px 기준 네 값 입력", "선형 vw 식 계산", "실시간 글자 미리보기", "CSS 코드 복사"],
      "inputs": [{"id":"sizes","label":"최소·최대 크기","type":"number"},{"id":"viewports","label":"최소·최대 뷰포트","type":"number"}],
      "steps": ["최소·최대 글자 크기를 px로 입력합니다.", "변화가 시작되고 끝날 뷰포트 폭을 입력합니다.", "계산된 clamp 식과 미리보기를 확인해 복사합니다."],
      "details": ["CSS clamp는 화면 폭에 따라 글자 크기나 여백을 부드럽게 바꾸되 지정한 최소값과 최대값을 넘지 않게 합니다. 네 개의 기준값으로 선형 보간식을 계산해 직접 기울기를 구하는 수고를 줄입니다.", "결과는 px와 vw를 조합한 CSS 값으로 제공됩니다. 실제 디자인에서는 브라우저 확대와 접근성을 고려해 rem 기반 최소·최대값을 사용하는 방법도 함께 검토하세요."],
      "faq": [{"question":"clamp의 세 값은 무엇인가요?","answer":"최소값, 화면 폭에 따라 변하는 선호값, 최대값 순서입니다."},{"question":"최소 뷰포트가 최대보다 커도 되나요?","answer":"아니요. 변화 구간을 계산하려면 최대 뷰포트가 최소보다 커야 합니다."},{"question":"글자 크기 외에도 쓸 수 있나요?","answer":"네. 같은 단위를 쓰는 여백, 폭, 간격 등에도 계산식을 적용할 수 있습니다."},{"question":"결과를 그대로 사용하면 되나요?","answer":"기본 선형식으로 쓸 수 있지만 실제 레이아웃의 최소·최대 화면에서 한 번 더 확인하세요."}],
      "tags": ["CSS", "clamp", "반응형글자", "웹디자인", "프론트엔드"],
      "keywords": ["CSS clamp 계산기","반응형 글자 크기","fluid typography","clamp calculator","vw 계산","CSS 선형 보간","responsive font size","최소 최대 글자","뷰포트 계산","CSS font clamp","clamp 식 만들기","프론트엔드 계산기","반응형 CSS","fluid size","CSS min max","글자 크기 자동","웹 디자인 계산","viewport width formula","vw px 변환 식","CSS 코드 복사","반응형 여백","clamp 미리보기","타이포그래피 계산","모바일 데스크톱 글자"],
      "summary": "네 기준값으로 반응형 CSS clamp 식을 만드는 최초 버전입니다.",
      "changes": ["최소·최대 크기와 뷰포트 입력", "선형 clamp 식과 미리보기", "입력 검증·KOR / ENG·코드 복사"],
      "qa": ["경계값·역전값·미리보기 확인", "375px 모바일 가로 넘침 확인", "KOR / ENG와 iframe 높이 확인"]
    }
  ]
}
