{
  "runId": "20260719-030518-hard",
  "workflow": "hard",
  "status": "completed",
  "confirm": "Y",
  "startedAt": "2026-07-19T03:05:18+09:00",
  "completedAt": "2026-07-19T03:39:35+09:00",
  "confirmedAt": "2026-07-19T03:56:28+09:00",
  "summary": "공개 모듈 28개 전수조사, 기존 도구 개선 6건, 신규·통합 페이지 3건과 공통 결함 수정 2건을 구현하고 Blogger·GitHub Pages 공개 검증을 완료했습니다.",
  "normalizedRequest": {
    "workType": "full-public-audit-improve-new-merge",
    "targets": [
      "all-published-tools"
    ],
    "versionLevel": "impact-selected",
    "bloggerPublish": true,
    "gitDeploy": true,
    "shutdown": false
  },
  "runState": {
    "current": "confirm",
    "stages": {
      "select": {
        "status": "completed",
        "startedAt": "2026-07-19T03:05:18+09:00",
        "completedAt": "2026-07-19T03:11:00+09:00",
        "evidence": [
          "공개 도구 28개 전수조사 범위 확정",
          "종료 예약 사용 안 함 확인",
          "375×812와 1280×900 공개 화면 사전 측정"
        ],
        "blockCode": null
      },
      "implement": {
        "status": "completed",
        "startedAt": "2026-07-19T03:11:00+09:00",
        "completedAt": "2026-07-19T03:27:00+09:00",
        "evidence": [
          "공개 도구 개선 6건",
          "XML·URL 신규 도구 2건",
          "data-size-converter를 date-calculator로 통합하고 기존 주소 보존",
          "장문 입력 공통 CSS·공개 감사 스크립트 추가"
        ],
        "blockCode": null
      },
      "validate": {
        "status": "completed",
        "startedAt": "2026-07-19T03:27:00+09:00",
        "completedAt": "2026-07-19T03:29:00+09:00",
        "evidence": [
          "181개 JSON 및 최신 릴리스 경로 통과",
          "25개 레지스트리 28개 모듈 계약 통과",
          "변경 HTML 인라인 스크립트와 신규 ES 모듈 문법 통과",
          "공개 감사 구조 검사 29개 통과"
        ],
        "blockCode": null
      },
      "publish": {
        "status": "completed",
        "startedAt": "2026-07-19T03:28:00+09:00",
        "completedAt": "2026-07-19T03:30:00+09:00",
        "evidence": [
          "Blogger 기존 게시글 8개 갱신",
          "XML 검사·정리 도구와 URL 분석·쿼리 편집기 LIVE 신규 발행",
          "Blogger URL 동기화 0건 불일치"
        ],
        "blockCode": null
      },
      "commit": {
        "status": "completed",
        "startedAt": "2026-07-19T03:30:00+09:00",
        "completedAt": "2026-07-19T03:32:12+09:00",
        "evidence": [
          "6f9f71a8c809aa1a1b373839960e236d16c11f67",
          "origin/main 푸시 완료"
        ],
        "blockCode": null
      },
      "deploy": {
        "status": "completed",
        "startedAt": "2026-07-19T03:32:12+09:00",
        "completedAt": "2026-07-19T03:39:35+09:00",
        "evidence": [
          "pages-build-deployment 29656055345 success",
          "Update tool catalog 29656055719 success",
          "변경 대상 10개 공개 모바일·데스크톱 재검사",
          "신규 Blogger 게시글 2개 H1·iframe·FAQ·패치노트 확인"
        ],
        "blockCode": null
      },
      "confirm": {
        "status": "completed",
        "startedAt": "2026-07-19T03:56:28+09:00",
        "completedAt": "2026-07-19T03:56:28+09:00",
        "evidence": [
          "사용자 확인 완료"
        ],
        "blockCode": null
      }
    }
  },
  "selectedTools": [
    "qr-barcode-generator",
    "json-tools",
    "base64-tools",
    "text-diff-checker",
    "markdown-preview-converter",
    "unicode-inspector",
    "date-calculator",
    "data-size-converter",
    "xml-formatter-validator",
    "url-parser-builder"
  ],
  "selectionBasis": "전체 공개 도구를 먼저 같은 기준으로 조사한 뒤 증거가 확인된 결함과 순환 기준으로 개선 대상을 선정",
  "changes": [
    {
      "target": "qr-barcode-generator",
      "version": "0.5.5v",
      "result": "문서 제목과 모바일 viewport 보완"
    },
    {
      "target": "json-tools",
      "version": "0.7.1v",
      "result": "문서 제목·viewport와 직접 입력 5MB 제한"
    },
    {
      "target": "base64-tools",
      "version": "0.9.3v",
      "result": "복사 차단 시 모바일 강제 선택 제거"
    },
    {
      "target": "text-diff-checker",
      "version": "0.0.3v",
      "result": "두 장문 입력을 위아래 전체 폭으로 고정"
    },
    {
      "target": "markdown-preview-converter",
      "version": "0.0.3v",
      "result": "장문 편집과 미리보기를 위아래 전체 폭으로 고정"
    },
    {
      "target": "unicode-inspector",
      "version": "0.0.2v",
      "result": "넓은 결과 표 키보드 스크롤 영역 제공"
    },
    {
      "target": "date-calculator",
      "version": "1.1.0v",
      "result": "SI·IEC 모든 데이터 단위 결과 표 통합"
    },
    {
      "target": "data-size-converter",
      "version": "0.1.0v",
      "result": "date-calculator 대체 관계와 기존 주소 호환 안내"
    },
    {
      "target": "xml-formatter-validator",
      "version": "0.0.1v",
      "result": "XML 검사·정리·압축·복사·저장 신규 공개"
    },
    {
      "target": "url-parser-builder",
      "version": "0.0.1v",
      "result": "URL 구성요소와 쿼리 반복 행 편집 신규 공개"
    }
  ],
  "newIdeas": [],
  "commonModules": [
    {
      "target": "longtext-layout",
      "result": "장문 입력 위아래 한 열 공통 CSS와 PORTRAIT_LONG_TEXT_SQUEEZE 회귀 계약"
    },
    {
      "target": "public-tool-audit",
      "result": "공개 카탈로그 전체 구조 검사 스크립트와 전수조사 보고서"
    },
    {
      "target": "retired-post-builder",
      "result": "일반 통합 게시글에 게임 전용 문구가 섞이지 않도록 대체 유형별 문구 분리"
    }
  ],
  "knowledgeOptimization": {
    "policyVersion": "0.2.0",
    "applied": [
      "OPT-001"
    ],
    "recorded": [],
    "skipped": [],
    "measuredReduction": {
      "before": 979,
      "after": 194,
      "unit": "duplicated automation instruction characters",
      "reduction": 0.8018
    }
  },
  "developmentTokenEfficiency": {
    "measurementStatus": "proxy_only",
    "baselineRunId": null,
    "tokens": {
      "baseline": null,
      "current": null,
      "accountingMethod": null
    },
    "instructionReduction": {
      "before": 979,
      "after": 194,
      "unit": "duplicated automation instruction characters",
      "reduction": 0.8018
    },
    "overallReduction": null,
    "proxies": [
      {
        "metric": "automation instruction characters",
        "before": 979,
        "after": 194,
        "reduction": 0.8018
      },
      {
        "metric": "startup result files read",
        "before": 3,
        "after": 1,
        "reduction": 0.6667
      }
    ],
    "note": "비교 가능한 전체 개발 토큰 수가 제공되지 않아 전체 감소율은 확정하지 않음"
  },
  "validation": [
    "기존 공개 도구 28개 모바일·데스크톱 사전 화면 측정",
    "181개 JSON과 모든 최신 릴리스 경로 통과",
    "25개 모듈 레지스트리 28개 계약 통과",
    "공개 카탈로그 구조 검사 29개 통과",
    "변경 HTML과 신규 ES 모듈 문법 통과",
    "변경 대상 10개 공개 375×812·1280×900 가로 넘침·hidden 누출·콘솔 오류 없음",
    "XML 정상·오류, URL 반복 행·재구성, 데이터 단위 9개 결과 표 동작 확인",
    "신규 Blogger 게시글 2개 H1·iframe·FAQ·누적 패치노트 확인"
  ],
  "blogger": {
    "created": [
      "https://bloggiedh.blogspot.com/2026/07/xml.html",
      "https://bloggiedh.blogspot.com/2026/07/url_01194177481.html"
    ],
    "updated": [
      "https://bloggiedh.blogspot.com/2026/07/blog-post.html",
      "https://bloggiedh.blogspot.com/2026/07/json.html",
      "https://bloggiedh.blogspot.com/2026/07/base64.html",
      "https://bloggiedh.blogspot.com/2026/07/blog-post_912.html",
      "https://bloggiedh.blogspot.com/2026/07/html.html",
      "https://bloggiedh.blogspot.com/2026/07/blog-post_273.html",
      "https://bloggiedh.blogspot.com/2026/07/blog-post_704.html",
      "https://bloggiedh.blogspot.com/2026/07/blog-post_112.html"
    ],
    "skipped": [],
    "status": "completed"
  },
  "git": {
    "branch": "main",
    "commit": "6f9f71a8c809aa1a1b373839960e236d16c11f67",
    "pushed": true
  },
  "deployment": {
    "status": "completed",
    "urls": [
      "https://leedohon.github.io/toolbox-project/embed/text-diff-checker/",
      "https://leedohon.github.io/toolbox-project/embed/markdown-preview-converter/",
      "https://leedohon.github.io/toolbox-project/embed/date-calculator/?mode=data",
      "https://leedohon.github.io/toolbox-project/embed/xml-formatter-validator/",
      "https://leedohon.github.io/toolbox-project/embed/url-parser-builder/",
      "https://bloggiedh.blogspot.com/2026/07/xml.html",
      "https://bloggiedh.blogspot.com/2026/07/url_01194177481.html"
    ]
  },
  "shutdown": {
    "requested": false,
    "scheduled": false,
    "input": "아니오",
    "scheduledFor": null,
    "cancelled": false
  },
  "blocked": [],
  "reportHistory": []
}
